{
  "cropsafe agro services": 1748824403033,
  "innovius resources and solutions limited": 1748827763706,
  "zeeks homes": 1748828426701,
  "prime incorporation": 1748828427180,
  "khenpro global services": 1748828427640,
  "smash technology": 1748828712071,
  "alfred & victoria associates": 1748828712444,
  "woodgate structure limited": 1748828713521,
  "ipnx nigeria limited": [
    {
      "site": "Example Site",
      "id": "7404dab744617c4e005220b8b2608298",
      "timestamp": 1748869291184
    },
    {
      "site": "JobGurus",
      "id": "7404dab744617c4e005220b8b2608298",
      "timestamp": 1748900381675
    }
  ],
  "excel and grace consulting": [
    {
      "site": "Example Site",
      "id": "f1167244121b741022b43c1a62c1b5b7",
      "timestamp": 1748869291184
    },
    {
      "site": "JobGurus",
      "id": "f1167244121b741022b43c1a62c1b5b7",
      "timestamp": 1748900381675
    },
    {
      "site": "JobGurus",
      "id": "887d4531103baa2671ea09fc3ee66bd3",
      "timestamp": 1748953945393
    }
  ],
  "amecron nigeria limited": [
    {
      "site": "Example Site",
      "id": "54f9211cf528b0b0c75d8628cb192dd2",
      "timestamp": 1748869291184
    },
    {
      "site": "Example Site",
      "id": "215afdcaaf6cbc45fbfeb4bc9b30a6f5",
      "timestamp": 1748870501361
    },
    {
      "site": "JobGurus",
      "id": "54f9211cf528b0b0c75d8628cb192dd2",
      "timestamp": 1748900381675
    }
  ],
  "dag industries nigeria limited": [
    {
      "site": "Example Site",
      "id": "b9a47fc979a105fa178c0a6ff600196f",
      "timestamp": 1748869291184
    },
    {
      "site": "Example Site",
      "id": "c65f9e18aef5d89c2e2e023fca7d8852",
      "timestamp": 1748869291184
    },
    {
      "site": "JobGurus",
      "id": "b9a47fc979a105fa178c0a6ff600196f",
      "timestamp": 1748900381675
    }
  ],
  "compovine technologies limited": [
    {
      "site": "Example Site",
      "id": "759e4f470c9aa0ab82fa3ad8b0037491",
      "timestamp": 1748870050188
    }
  ],
  "the concept group": [
    {
      "site": "Example Site",
      "id": "d9701fcff62c06b239e560da20a5ec79",
      "timestamp": 1748870050188
    }
  ],
  "triple x environmental health consult": [
    {
      "site": "Example Site",
      "id": "726439ffe83eaef20fd62228749fcc82",
      "timestamp": 1748870050188
    },
    {
      "site": "Example Site",
      "id": "038fcad25f1c3b083fd2d2870d17baac",
      "timestamp": 1748870050188
    }
  ],
  "pharma recruiter": [
    {
      "site": "Example Site",
      "id": "63e629ce954f51b931ba08972c91194e",
      "timestamp": 1748870050188
    }
  ],
  "bold & timeless (bt)": [
    {
      "site": "Example Site",
      "id": "331fbd695dcd63d370f9e8470cebac0f",
      "timestamp": 1748870501361
    }
  ],
  "smartrecruitmentnow": [
    {
      "site": "Example Site",
      "id": "2fca53d2defb7c40efe0265ce5c37f25",
      "timestamp": 1748870501361
    }
  ],
  "f-pro computer college": [
    {
      "site": "Example Site",
      "id": "b48ada796265ed000d80c68eddede43d",
      "timestamp": 1748870501361
    }
  ],
  "jesuit memorial college": [
    {
      "site": "Example Site",
      "id": "381258be8038d4088ecb918aaed800bf",
      "timestamp": 1748870501361
    }
  ],
  "carrot-top drugs limited": [
    {
      "site": "Example Site",
      "id": "61ebd172c52c15fbfa77437fbc768143",
      "timestamp": 1748870561278
    }
  ],
  "african industries group": [
    {
      "site": "Example Site",
      "id": "94b7ea8f569c1ef319ba965b542e50ce",
      "timestamp": 1748870561278
    }
  ],
  "residency hotel limited": [
    {
      "site": "Example Site",
      "id": "2dfd9cceb6c8baf7d115d9065a183e35",
      "timestamp": 1748870561278
    }
  ],
  "dangote group": [
    {
      "site": "Example Site",
      "id": "931a4b36a0363d1a3091f995fafc4d41",
      "timestamp": 1748870561278
    },
    {
      "site": "JobGurus",
      "id": "ed021726df1a03209ab5850fd1887342",
      "timestamp": 1748949214016
    }
  ],
  "cway group": [
    {
      "site": "Example Site",
      "id": "3c0add773c170b00991dadb686c174ec",
      "timestamp": 1748870561278
    }
  ],
  "natnudo": [
    {
      "site": "Example Site",
      "id": "25a89758b61e47258a160872980eace0",
      "timestamp": 1748891054257
    },
    {
      "site": "Example Site",
      "id": "c9c927eaf62f809d65c34b423558416f",
      "timestamp": 1748891054257
    },
    {
      "site": "Example Site",
      "id": "5cac91944f2a0bdf1533fdf7b2aaffca",
      "timestamp": 1748891054257
    },
    {
      "site": "JobGurus",
      "id": "25a89758b61e47258a160872980eace0",
      "timestamp": 1748893788721
    },
    {
      "site": "JobGurus",
      "id": "c9c927eaf62f809d65c34b423558416f",
      "timestamp": 1748893788721
    },
    {
      "site": "JobGurus",
      "id": "5cac91944f2a0bdf1533fdf7b2aaffca",
      "timestamp": 1748893788721
    }
  ],
  "aaa finance and investment company limited": [
    {
      "site": "Example Site",
      "id": "a3471bd8a4afa1eff4b0e0db8addc9bf",
      "timestamp": 1748891054257
    },
    {
      "site": "JobGurus",
      "id": "a3471bd8a4afa1eff4b0e0db8addc9bf",
      "timestamp": 1748893788721
    },
    {
      "site": "JobGurus",
      "id": "65fb4b0588b366367499f72e0d6f5878",
      "timestamp": 1748897149712
    }
  ],
  "o j wale pillars metal and tech limited": [
    {
      "site": "Example Site",
      "id": "dba95c7fce4dc2439d67fbb0a7e3eaa3",
      "timestamp": 1748891054257
    },
    {
      "site": "JobGurus",
      "id": "dba95c7fce4dc2439d67fbb0a7e3eaa3",
      "timestamp": 1748893788721
    }
  ],
  "pg consulting limited": [
    {
      "site": "JobGurus",
      "id": "312ee8c77f43addb3dde253229d1f082",
      "timestamp": 1748897149712
    },
    {
      "site": "JobGurus",
      "id": "9ab3a3fe4117381d94e487fd49780f1e",
      "timestamp": 1748897149712
    }
  ],
  "xora technologies limited": [
    {
      "site": "JobGurus",
      "id": "2e7a37330b3ee4e6b30133f2f043a561",
      "timestamp": 1748897149712
    }
  ],
  "outcess solutions nigeria limited": [
    {
      "site": "JobGurus",
      "id": "3e70d0a22d62764af41faa0b4b89d3c8",
      "timestamp": 1748897149712
    }
  ],
  "sap nigeria": [
    {
      "site": "JobGurus",
      "id": "0ba73325a3a3317236ad048df367b188",
      "timestamp": 1748898922757
    }
  ],
  "choice talents ng": [
    {
      "site": "JobGurus",
      "id": "9da9ea3b2985b8c4977e18f95c68f7af",
      "timestamp": 1748898922757
    }
  ],
  "greengrass investment limited": [
    {
      "site": "JobGurus",
      "id": "6be9f53dd12786784ab3e31c230dc621",
      "timestamp": 1748898922757
    }
  ],
  "promasidor": [
    {
      "site": "JobGurus",
      "id": "75dbe25cfdf68914b3f3d7345f68fc51",
      "timestamp": 1748898922757
    }
  ],
  "jc international": [
    {
      "site": "JobGurus",
      "id": "5b2900fadeb1b48ff02bfbfad518ee33",
      "timestamp": 1748898922757
    }
  ],
  "trinity financial": [
    {
      "site": "JobGurus",
      "id": "5e73ed1ec7dbbb5ca3151fdfab92fc38",
      "timestamp": 1748900381675
    }
  ],
  "a&r group": [
    {
      "site": "JobGurus",
      "id": "920a7e1a4aef2848b5fcdd98d237edbe",
      "timestamp": 1748942241466
    }
  ],
  "howbury school": [
    {
      "site": "JobGurus",
      "id": "cfdc5cb17eae233e698653c1e0475533",
      "timestamp": 1748942241466
    }
  ],
  "jobvet services": [
    {
      "site": "JobGurus",
      "id": "81209ea3fecce1ec9b8e14b3134e675f",
      "timestamp": 1748942241466
    }
  ],
  "jamub group": [
    {
      "site": "JobGurus",
      "id": "2bbc4d9091e345a4bec1f5f4f5449d4e",
      "timestamp": 1748942241466
    }
  ],
  "ziba consulting": [
    {
      "site": "JobGurus",
      "id": "e0ecf183c7fc8235e6cb70f1a99aa087",
      "timestamp": 1748943708802
    },
    {
      "site": "JobGurus",
      "id": "21455f9c896abc460f0341b1a89ef152",
      "timestamp": 1748958720164
    }
  ],
  "castville solutions": [
    {
      "site": "JobGurus",
      "id": "adc3d390e9eb06bda12cfd40da53c83e",
      "timestamp": 1748943708802
    },
    {
      "site": "JobGurus",
      "id": "3b7d354b4d7a422de34c89e981f2e3d3",
      "timestamp": 1748945837932
    }
  ],
  "lacare staffing solutions": [
    {
      "site": "JobGurus",
      "id": "97465f8fa4327431e4b1f6bde8bfb075",
      "timestamp": 1748943708802
    }
  ],
  "wandel international": [
    {
      "site": "JobGurus",
      "id": "59db9c931fd17570101ee70af8de9dc4",
      "timestamp": 1748943708802
    }
  ],
  "airtel nigeria": [
    {
      "site": "JobGurus",
      "id": "a789f9f81aa317cb3b8ce083d604d471",
      "timestamp": 1748943708802
    }
  ],
  "hea group": [
    {
      "site": "JobGurus",
      "id": "ad8359c54f2814e05153c721494cbe48",
      "timestamp": 1748945837932
    }
  ],
  "femaus consults": [
    {
      "site": "JobGurus",
      "id": "db16f6abf3f28a20d97b831699c91444",
      "timestamp": 1748945837932
    },
    {
      "site": "JobGurus",
      "id": "a6213b0f08803d16ca3331efa705f5ff",
      "timestamp": 1748957407033
    }
  ],
  "mshel homes limited": [
    {
      "site": "JobGurus",
      "id": "585a27aa47bc61e4e9d80efe025485ea",
      "timestamp": 1748945837932
    }
  ],
  "dana group": [
    {
      "site": "JobGurus",
      "id": "97d1c1589c00466d6d63d374482fd5ba",
      "timestamp": 1748945837932
    }
  ],
  "raphael group": [
    {
      "site": "JobGurus",
      "id": "077f95cfe54ed621525128e7b9ff5698",
      "timestamp": 1748947530707
    },
    {
      "site": "JobGurus",
      "id": "12ebd66f5c0b0127c192dac3b5471e88",
      "timestamp": 1748947530707
    }
  ],
  "debmyk consult": [
    {
      "site": "JobGurus",
      "id": "a3129d3f7795ec4a6919e7c379186b1e",
      "timestamp": 1748947530707
    }
  ],
  "lgv gas systems": [
    {
      "site": "JobGurus",
      "id": "5f26a8f56ac8bc1ae4a9fb9ef23c515b",
      "timestamp": 1748949214016
    }
  ],
  "sagar vitaceuticals nigeria limited": [
    {
      "site": "JobGurus",
      "id": "a8820c3cdd4dcd28f8f1509356420d55",
      "timestamp": 1748949214016
    }
  ],
  "radisson hotel group": [
    {
      "site": "JobGurus",
      "id": "0c4f3778f5b30736368d18d7b619050e",
      "timestamp": 1748949214016
    }
  ],
  "reliance hmo": [
    {
      "site": "JobGurus",
      "id": "cd0086d9a74462a1abe715468ce0c393",
      "timestamp": 1748949214016
    }
  ],
  "me cure industries limited": [
    {
      "site": "JobGurus",
      "id": "1f099a7e9bc660aaebbc9df4651ea62a",
      "timestamp": 1748950619805
    }
  ],
  "society for family health (sfh)": [
    {
      "site": "JobGurus",
      "id": "3466afc3cbf966c49bb535de9e38fffe",
      "timestamp": 1748950619805
    }
  ],
  "clinix healthcare": [
    {
      "site": "JobGurus",
      "id": "f725d0f1be0a2cd06ff98809db9ca0d3",
      "timestamp": 1748950619805
    }
  ],
  "dgic international business services limited": [
    {
      "site": "JobGurus",
      "id": "d4050538a3e0ac7753f85ff6f74552ab",
      "timestamp": 1748950619805
    }
  ],
  "glyde lubricants limited": [
    {
      "site": "JobGurus",
      "id": "cff0c3cd10eca078881f7120499cd828",
      "timestamp": 1748950619805
    }
  ],
  "pruvia integrated limited": [
    {
      "site": "JobGurus",
      "id": "ea0a89865aff3c750da86cdd5af94b9b",
      "timestamp": 1748953945393
    }
  ],
  "cig motors co. limited": [
    {
      "site": "JobGurus",
      "id": "cfa0ff6ed8980584493041d4aa3b0183",
      "timestamp": 1748953945393
    }
  ],
  "first excelsia professional services limited": [
    {
      "site": "JobGurus",
      "id": "e7d949be26c87167e798ae6956a61540",
      "timestamp": 1748953945393
    }
  ],
  "universal human resource consult": [
    {
      "site": "JobGurus",
      "id": "6e0d8eeabb5e72cb1349e21e4df4b26d",
      "timestamp": 1748953945393
    }
  ],
  "above lifestyle": [
    {
      "site": "JobGurus",
      "id": "436dc8fdbbee996c5215fcdacb1e8808",
      "timestamp": 1748957407033
    }
  ],
  "cfao yamaha motor": [
    {
      "site": "JobGurus",
      "id": "fc8cec40e54791e8cd057e2556c69f08",
      "timestamp": 1748957407033
    }
  ],
  "filmhouse cinemas limited": [
    {
      "site": "JobGurus",
      "id": "7444e9e2e8f067140fa2d4c88dcf094b",
      "timestamp": 1748957407033
    }
  ],
  "ascentech services limited": [
    {
      "site": "JobGurus",
      "id": "bfbae501f6947b48480f5c7fcb5e66cf",
      "timestamp": 1748958720164
    },
    {
      "site": "JobGurus",
      "id": "32c64210b60e173f4cffaa53866fa89d",
      "timestamp": 1749037075571
    }
  ],
  "abbfem group": [
    {
      "site": "JobGurus",
      "id": "b0ac0096c8c3f2bf4c09f9350273e607",
      "timestamp": 1748960171254
    }
  ],
  "eshopafrica logistics": [
    {
      "site": "JobGurus",
      "id": "90cd17f6cff470587b4fd3ee0f62a270",
      "timestamp": 1748960171254
    }
  ],
  "renmoney": [
    {
      "site": "JobGurus",
      "id": "ae4334f09e15827ad57a7173a87b55a3",
      "timestamp": 1748960171254
    },
    {
      "site": "JobGurus",
      "id": "358a28523dd8e4b729dcff542ca57cf4",
      "timestamp": 1748960171254
    }
  ],
  "teamace limited": [
    {
      "site": "JobGurus",
      "id": "b78884dd38eaa5d17310356277cd17f5",
      "timestamp": 1748962033525
    }
  ],
  "food concepts plc": [
    {
      "site": "JobGurus",
      "id": "c4306f38fee7327c146a2fe2dd70a406",
      "timestamp": 1748962033525
    }
  ],
  "divine infinity college": [
    {
      "site": "JobGurus",
      "id": "a6852b8748d73feb37521aa15892b826",
      "timestamp": 1748962033525
    },
    {
      "site": "JobGurus",
      "id": "7ea827f66009fb7eb86d9f4206dd05f5",
      "timestamp": 1748963878938
    }
  ],
  "alan & grant": [
    {
      "site": "JobGurus",
      "id": "e2991ea205bddd56576d0920b6448133",
      "timestamp": 1749032250374
    },
    {
      "site": "JobGurus",
      "id": "cabd11d80ddd84542036a76eb23b69ab",
      "timestamp": 1749032250374
    }
  ],
  "vantegral consulting": [
    {
      "site": "JobGurus",
      "id": "5b7ac8df1a03e7c2d8e406da477c6867",
      "timestamp": 1749033883448
    }
  ],
  "private sector health alliance of nigeria": [
    {
      "site": "JobGurus",
      "id": "8254c5b797ddef39c7f46fd0ffa96afe",
      "timestamp": 1749033883448
    }
  ],
  "jijedapt human resources consult limited": [
    {
      "site": "JobGurus",
      "id": "30e08b50e95354b69b63f7d55b39275c",
      "timestamp": 1749033883448
    }
  ],
  "lisse africa": [
    {
      "site": "JobGurus",
      "id": "906ba95e17ceffe64692c42617c67e4d",
      "timestamp": 1749033883448
    }
  ],
  "guo transport company": [
    {
      "site": "JobGurus",
      "id": "b8d9ba2c5691424db0e913752c23e310",
      "timestamp": 1749033883448
    }
  ],
  "allen professional services": [
    {
      "site": "JobGurus",
      "id": "d0fcb3b68702af7439a4e86fd50582d2",
      "timestamp": 1749035609906
    },
    {
      "site": "JobGurus",
      "id": "dcb74c25074c31e01d57bbfc999e6cb8",
      "timestamp": 1749035609906
    }
  ],
  "julius berger nigeria plc": [
    {
      "site": "JobGurus",
      "id": "3336428682307fe8e5b41ebc3f7be975",
      "timestamp": 1749037075571
    }
  ],
  "estrada international staffing solutions": [
    {
      "site": "JobGurus",
      "id": "e2761ea65d05c389ec96956ceabfa815",
      "timestamp": 1749037075571
    }
  ],
  "startup soar": [
    {
      "site": "JobGurus",
      "id": "cd9b23cbb02cb5a3ee69e201bb36ff36",
      "timestamp": 1749037075571
    }
  ],
  "ouranos technologies (ouranos)": [
    {
      "site": "JobGurus",
      "id": "02ea40322b7d547ac4388d2064c956f6",
      "timestamp": 1749037075571
    }
  ],
  "salpha energy limited": [
    {
      "site": "JobGurus",
      "id": "d61a83c7932b3472106e284df20698e7",
      "timestamp": 1749040343659
    },
    {
      "site": "JobGurus",
      "id": "5d81724223f0df1a2267d9f3b207f491",
      "timestamp": 1749040343659
    },
    {
      "site": "JobGurus",
      "id": "e6f38814724a74e92ad2b44c3570111b",
      "timestamp": 1749040343659
    }
  ],
  "greensprings school": [
    {
      "site": "JobGurus",
      "id": "a3c143a6324c385bee1976b6198a1fee",
      "timestamp": 1749040343659
    }
  ],
  "equinix": [
    {
      "site": "JobGurus",
      "id": "e9a6c303e1698f5ffe35be3217bc285b",
      "timestamp": 1749040343659
    }
  ],
  "premier hub innovation center": [
    {
      "site": "JobGurus",
      "id": "1d573d72313d59d05e6a2576e3ab8f9b",
      "timestamp": 1749043867108
    }
  ],
  "tek experts": [
    {
      "site": "JobGurus",
      "id": "d56828249e12dffa150de2fcf829111a",
      "timestamp": 1749046391159
    }
  ],
  "presto integrated solutions": [
    {
      "site": "JobGurus",
      "id": "1414b039d1abf2959331e847113abdcb",
      "timestamp": 1749046391159
    }
  ],
  "chelis bookazine limited": [
    {
      "site": "JobGurus",
      "id": "b1716950bf5970acfd36e2ea362958e5",
      "timestamp": 1749046391159
    }
  ],
  "interrand group": [
    {
      "site": "JobGurus",
      "id": "c93807978b8a35f1da8db8ab018c3366",
      "timestamp": 1749046391159
    }
  ],
  "tivana workforce": [
    {
      "site": "JobGurus",
      "id": "7878692808dff997082196bec88db70e",
      "timestamp": 1749046391159
    },
    {
      "site": "JobGurus",
      "id": "2781236d9f5294c4531200dfa0785204",
      "timestamp": 1749053849200
    },
    {
      "site": "JobGurus",
      "id": "15a55a4f698a25cf5f1b68088c31b5a1",
      "timestamp": 1749053849200
    }
  ],
  "pennek nigeria limited": [
    {
      "site": "JobGurus",
      "id": "a6d44ff8e570d5ff8ed64117e065ee11",
      "timestamp": 1749049528578
    }
  ],
  "western development company limited": [
    {
      "site": "JobGurus",
      "id": "c7960a0f5e72c852e74c9917f36d8554",
      "timestamp": 1749049528578
    }
  ],
  "africa plus partners nigeria limited": [
    {
      "site": "JobGurus",
      "id": "5524b0b55453a837ec641bf8e1cf3e2c",
      "timestamp": 1749049528578
    }
  ],
  "optimus bank": [
    {
      "site": "JobGurus",
      "id": "d83dafd3ce29426b6209b05e91c99b23",
      "timestamp": 1749049528578
    }
  ],
  "mkh properties limited": [
    {
      "site": "JobGurus",
      "id": "6a119c65a87e4142561a2bd5e8d7d172",
      "timestamp": 1749049528578
    }
  ],
  "unocasa limited": [
    {
      "site": "JobGurus",
      "id": "d4c0de35c3c43ded799208ee4240bf6d",
      "timestamp": 1749052478703
    }
  ],
  "elvaridah limited": [
    {
      "site": "JobGurus",
      "id": "53afd8db8ccd15624dbb767245daf949",
      "timestamp": 1749052478703
    }
  ],
  "razley print limited": [
    {
      "site": "JobGurus",
      "id": "505be2939843ff0c1280bceb020f9c73",
      "timestamp": 1749052478703
    }
  ],
  "boctrust microfinance bank": [
    {
      "site": "JobGurus",
      "id": "2ec78b2cf5ed8105978589da6a9924ec",
      "timestamp": 1749052478703
    }
  ],
  "zigma limited": [
    {
      "site": "JobGurus",
      "id": "459aa10e4725a92abff9618cb1b00135",
      "timestamp": 1749053849200
    }
  ],
  "bat computer technologies limited": [
    {
      "site": "JobGurus",
      "id": "900eb3d66bbfbae25116069d399848d5",
      "timestamp": 1749053849200
    }
  ],
  "bolton white group": [
    {
      "site": "JobGurus",
      "id": "a697b9809327e8713a0798f65da13d19",
      "timestamp": 1749053849200
    }
  ],
  "mephalti technologies limited": [
    {
      "site": "JobGurus",
      "id": "f1467a45b7db0ac74e5622da6518652b",
      "timestamp": 1749118659769
    }
  ],
  "pause factory resources limited": [
    {
      "site": "JobGurus",
      "id": "e110b95b3616cc375d12177886a45974",
      "timestamp": 1749118659769
    }
  ],
  "nestoil plc": [
    {
      "site": "JobGurus",
      "id": "0887764c37bf6ce7e90108fde0fb709c",
      "timestamp": 1749120343530
    }
  ],
  "flexfilms limited": [
    {
      "site": "JobGurus",
      "id": "9a97edb548bde62ab24f4d2b4a262953",
      "timestamp": 1749120343530
    }
  ],
  "petrogap oil and gas limited": [
    {
      "site": "JobGurus",
      "id": "830c72243e4daa9cc4ca94271572e311",
      "timestamp": 1749120343530
    },
    {
      "site": "JobGurus",
      "id": "dc3f29cfec69c0c4ca55620d20dc06d1",
      "timestamp": 1749123428585
    }
  ],
  "jameda concepts": [
    {
      "site": "JobGurus",
      "id": "904998d2c79e097a1df6c35ca504d6fe",
      "timestamp": 1749122038903
    }
  ],
  "international flavors & fragrances": [
    {
      "site": "JobGurus",
      "id": "b5fddf28fc7cfa483a5a29c0f1d49e5e",
      "timestamp": 1749122038903
    }
  ],
  "libertypay": [
    {
      "site": "JobGurus",
      "id": "1494d6bf900ad59d4d49e140d55eec07",
      "timestamp": 1749122038903
    }
  ],
  "dp world": [
    {
      "site": "JobGurus",
      "id": "eb1911c1eb2ef6c932b7079e7fec6e3d",
      "timestamp": 1749122038903
    }
  ],
  "powered by health initiative": [
    {
      "site": "JobGurus",
      "id": "014a43ef6a16aa8bb169bec7cc73a50f",
      "timestamp": 1749123428585
    }
  ],
  "west africa vocational education (wave)": [
    {
      "site": "JobGurus",
      "id": "f8ff256f2c61a64871bdf1057e6bd4fd",
      "timestamp": 1749123428585
    }
  ],
  "skylight professional services and partners": [
    {
      "site": "JobGurus",
      "id": "2c67878011475a126f45aaf142df1d2f",
      "timestamp": 1749123428585
    }
  ],
  "workforce group": [
    {
      "site": "JobGurus",
      "id": "01c24157a18614dcb174f4291da423fe",
      "timestamp": 1749123428585
    }
  ],
  "zenith carex international limited": [
    {
      "site": "JobGurus",
      "id": "33806df03756888cb4538e50e9696930",
      "timestamp": 1749126736406
    },
    {
      "site": "JobGurus",
      "id": "75c77d23ec89c41ddce7c1a8d5a366fc",
      "timestamp": 1749126736406
    }
  ],
  "canonical nigeria": [
    {
      "site": "JobGurus",
      "id": "e017bd15b305276245f33a7a8515d96b",
      "timestamp": 1749126736406
    }
  ],
  "beebeejump international limited": [
    {
      "site": "JobGurus",
      "id": "6b516216df13c92a7b697d1261531e6b",
      "timestamp": 1749126736406
    }
  ],
  "elizabeth maddeux": [
    {
      "site": "JobGurus",
      "id": "c8d25167a0d66afd8dfc06182036ee4f",
      "timestamp": 1749126736406
    }
  ]
}